pimmsread/__init__.py
pimmsread/pimmsread.py
pimmsread/Subfunctions/__init__.py
pimmsread/Subfunctions/jit_functions.py
pimmsread-1.0.1.dist-info/licenses/LICENSE
pimmsread-1.0.1.dist-info/METADATA
pimmsread-1.0.1.dist-info/WHEEL
pimmsread-1.0.1.dist-info/top_level.txt
pimmsread-1.0.1.dist-info/RECORD
