Metadata-Version: 2.4
Name: pimmsread
Version: 1.0.1
Summary: Python package for reading PImMS data
Author-email: David Heathcote <david.heathcote@chem.ox.ac.uk>
Project-URL: Homepage, https://github.com/Vallance-Research-Group/pimmsread
Project-URL: Issues, https://github.com/Vallance-Research-Group/pimmsread/issues
Keywords: pimms,image,covariance
Classifier: Programming Language :: Python :: 3
Classifier: Operating System :: OS Independent
Requires-Python: >=3.5
License-File: LICENSE
Requires-Dist: numpy
Requires-Dist: numba
Dynamic: license-file
